antlr_ast.py
antlr_ast-0.2.1.dist-info/LICENSE
antlr_ast-0.2.1.dist-info/METADATA
antlr_ast-0.2.1.dist-info/WHEEL
antlr_ast-0.2.1.dist-info/top_level.txt
antlr_ast-0.2.1.dist-info/RECORD
