Metadata-Version: 2.1
Name: antlr-ast
Version: 0.2.1
Summary: AST shaping for antlr parsers
Home-page: https://github.com/datacamp/antlr-ast
Author: Michael Chow
Author-email: michael@datacamp.com
License: UNKNOWN
Platform: UNKNOWN
Requires-Dist: antlr4-python3-runtime
